client/__init__.py
client/client_run.py
client/decos.py
client/descriptors.py
client/errors.py
client/metaclass.py
client/client/__init__.py
client/client/add_contact.py
client/client/del_contact.py
client/client/main_window.py
client/client/main_window_conv.py
client/client/start_dialog.py
client/client/transport.py
client/common/__init__.py
client/common/errors.py
client/common/utils.py
client/common/variables.py
client/logs/__init__.py
client/logs/client_log_config.py
client/logs/server_log_config.py
client/unit_tests/__init__.py
client/unit_tests/test_client.py
client/unit_tests/test_server.py
client/unit_tests/test_utils.py
kodo_messenger_client-0.0.1.dist-info/METADATA
kodo_messenger_client-0.0.1.dist-info/WHEEL
kodo_messenger_client-0.0.1.dist-info/top_level.txt
kodo_messenger_client-0.0.1.dist-info/RECORD
